LICENSE
README.md
setup.py
laravel_ignition_rxss.egg-info/PKG-INFO
laravel_ignition_rxss.egg-info/SOURCES.txt
laravel_ignition_rxss.egg-info/dependency_links.txt
laravel_ignition_rxss.egg-info/entry_points.txt
laravel_ignition_rxss.egg-info/requires.txt
laravel_ignition_rxss.egg-info/top_level.txt
laravelignitionrxss/__init__.py
laravelignitionrxss/main.py
laravelignitionrxss/includes/__init__.py
laravelignitionrxss/includes/bot.py
laravelignitionrxss/includes/filereader.py
laravelignitionrxss/includes/scan.py
laravelignitionrxss/includes/writefile.py
laravelignitionrxss/utils/__init__.py
laravelignitionrxss/utils/configure.py
laravelignitionrxss/utils/const.py
laravelignitionrxss/utils/helpers.py
laravelignitionrxss/utils/status.py